ecgclock/__init__.py
ecgclock/cohort.py
ecgclock/ecgclock.py
ecgclock/ecgfigure.py
ecgclock/ecgmeasurements.py
ecgclock/hrderivclock.py
ecgclock/qtclock.py
ecgclock/recording.py
ecgclock/utils.py
ecgclock/ann_loaders/__init__.py
ecgclock/ann_loaders/compas.py
ecgclock/ann_loaders/csv.py
ecgclock/ann_loaders/gilead.py
ecgclock/example_data/baseline_eg.csv
ecgclock/example_data/baseline_eg_messy.csv
ecgclock/example_data/baseline_eg_noheads.csv
ecgclock/example_data/drug_eg.csv
ecgclock-2019.7.29.dist-info/METADATA
ecgclock-2019.7.29.dist-info/RECORD
ecgclock-2019.7.29.dist-info/WHEEL
ecgclock-2019.7.29.dist-info/entry_points.txt
ecgclock-2019.7.29.dist-info/top_level.txt
